drf_simplepermissions/__init__.py
drf_simplepermissions/exceptions.py
drf_simplepermissions/permissions.py
drf_simplepermissions-1.0.0.dist-info/METADATA
drf_simplepermissions-1.0.0.dist-info/WHEEL
drf_simplepermissions-1.0.0.dist-info/top_level.txt
drf_simplepermissions-1.0.0.dist-info/RECORD
