Metadata-Version: 2.1
Name: drf-simplepermissions
Version: 1.0.0
Summary: SimplePermissions checks against a list of permissions
Home-page: https://github.com/sensson/python-drf-simplepermissions
Author: Sensson BV
Author-email: info@sensson.net
License: UNKNOWN
Platform: UNKNOWN
Requires-Python: >=3.4
Requires-Dist: django
Requires-Dist: djangorestframework
